{"AutoEnableNames":["十六五夜@摩杜纳","无糖盐@摩杜纳"],"TempEnableButton":2,"TempDisableButton":1,"MainConfig":{"EnableQuestAccept":false,"EnableQuestComplete":false,"EnableRewardPick":false,"EnableRequestHandin":false,"EnableCutsceneEsc":false,"EnableCutsceneSkipConfirm":false,"EnableTalkSkip":true,"EnableRequestFill":false,"EnableAutoInteract":false,"QTIQuestEnabled":true,"QTIQuestColor":{"X":1.0,"Y":0.0,"Z":0.5176471,"W":1.0},"QTIQuestTether":true,"QTIQuestThickness":2.0,"QTIQuestHideWhenTargeted":false,"QTIAlwaysEnabled":false},"TerritoryConditions":{"984":{"EnableQuestAccept":false,"EnableQuestComplete":false,"EnableRewardPick":false,"EnableRequestHandin":false,"EnableCutsceneEsc":true,"EnableCutsceneSkipConfirm":true,"EnableTalkSkip":false,"EnableRequestFill":false,"EnableAutoInteract":false,"QTIQuestEnabled":true,"QTIQuestColor":{"X":1.0,"Y":0.0,"Z":0.5176471,"W":1.0},"QTIQuestTether":true,"QTIQuestThickness":2.0,"QTIQuestHideWhenTargeted":false,"QTIAlwaysEnabled":false},"962":{"EnableQuestAccept":true,"EnableQuestComplete":true,"EnableRewardPick":true,"EnableRequestHandin":true,"EnableCutsceneEsc":true,"EnableCutsceneSkipConfirm":false,"EnableTalkSkip":false,"EnableRequestFill":true,"EnableAutoInteract":false,"QTIQuestEnabled":true,"QTIQuestColor":{"X":1.0,"Y":0.0,"Z":0.5176471,"W":1.0},"QTIQuestTether":true,"QTIQuestThickness":2.0,"QTIQuestHideWhenTargeted":false,"QTIAlwaysEnabled":false}},"GlobalOverridesLocal":false,"EnableOverlay":false,"OverlayOffset":{"X":0.0,"Y":-10.0},"NotifyDisableManualState":false,"NotifyDisableOnLogin":false,"QTIEnabled":true,"PickRewardOrder":[1,4,2,0,3],"PickRewardSilent":false,"ENpcFinder":false,"EObjFinder":true,"FinderKey":162,"DontAutoDisable":true,"Navmesh":true,"NavmeshAutoInteract":true,"Mount":209,"NavStatusChat":true,"DisplayFunding":false,"EnableFlight":true,"AllowUnsafeOptions":null,"EnableTeleportToFlag":false,"QTAEnabledWhenTADisable":false,"QTAFinderEnabledWhenTADisable":false,"AutoInteractMaxRadius":10.0,"UseSprintPeloton":true,"Version":2}