{
  "DelayMS": 8000,
  "ShowInitialApocMove": true,
  "ShowMoveGuide": false,
  "ShowTankGuide": false,
  "TankDelayMS": 18000,
  "Priority": {
    "Name": "Priority list",
    "Description": "",
    "PriorityLists": [
      {
        "List": [
          {
            "Name": "",
            "Jobs": [],
            "Role": 0
          },
          {
            "Name": "",
            "Jobs": [],
            "Role": 0
          },
          {
            "Name": "",
            "Jobs": [],
            "Role": 0
          },
          {
            "Name": "",
            "Jobs": [],
            "Role": 0
          }
        ],
        "IsRole": false
      }
    ]
  },
  "SelectedPositions": [],
  "IsLeftStack": false,
  "OriginalSpreads": false,
  "IsDifferentSafeSpots": false,
  "SelectedPositionsAlt": []
}